setup.py
marketo/__init__.py
marketo/auth.py
marketo/rfc3339.py
marketo/version.py
marketo.egg-info/PKG-INFO
marketo.egg-info/SOURCES.txt
marketo.egg-info/dependency_links.txt
marketo.egg-info/requires.txt
marketo.egg-info/top_level.txt
marketo/wrapper/__init__.py
marketo/wrapper/get_lead.py
marketo/wrapper/get_lead_activity.py
marketo/wrapper/lead_activity.py
marketo/wrapper/lead_record.py
marketo/wrapper/request_campaign.py
marketo/wrapper/sync_lead.py