Metadata-Version: 1.0
Name: marketo
Version: 0.1.0
Summary: marketo-python is a python query client that wraps the Marketo SOAP API.
Home-page: https://github.com/segmentio/marketo-python
Author: Segment.io
Author-email: friends@segment.io
License: MIT License
Platform: UNKNOWN
